[
  {
    "sn": "1.",
    "name": "ABEL OLUWAFIMIDARARERE",
    "sex": "F",
    "class": "JSS 1",
    "section": "Secondary",
    "admissionNumber": "WIN/2016/001"
  },
  {
    "sn": "2.",
    "name": "ABOLARIN ENIOLA",
    "sex": "F",
    "class": "JSS 1",
    "section": "Secondary",
    "admissionNumber": "WIN/2016/002"
  },
  {
    "sn": "3.",
    "name": "ADEKUNLE OLAMIDE",
    "sex": "F",
    "class": "JSS 1",
    "section": "Secondary",
    "admissionNumber": "WIN/2016/003"
  },
  {
    "sn": "4.",
    "name": "ADEOYE PAUL WILLIAM",
    "sex": "M",
    "class": "JSS 1",
    "section": "Secondary",
    "admissionNumber": "WIN/2016/004"
  },
  {
    "sn": "5.",
    "name": "ADEYEMI ANUOLUWAPO",
    "sex": "M",
    "class": "JSS 1",
    "section": "Secondary",
    "admissionNumber": "WIN/2016/005"
  },
  {
    "sn": "6.",
    "name": "AITOKHAIMEN PRECIOUS",
    "sex": "F",
    "class": "JSS 1",
    "section": "Secondary",
    "admissionNumber": "WIN/2016/006"
  },
  {
    "sn": "7.",
    "name": "AKOLERY ABIGAIL",
    "sex": "F",
    "class": "JSS 1",
    "section": "Secondary",
    "admissionNumber": "WIN/2016/007"
  },
  {
    "sn": "8.",
    "name": "AWOLESI ABDULMALIK",
    "sex": "M",
    "class": "JSS 1",
    "section": "Secondary",
    "admissionNumber": "WIN/2016/008"
  },
  {
    "sn": "9.",
    "name": "BALOGUN ANJOLAOLUWA",
    "sex": "F",
    "class": "JSS 1",
    "section": "Secondary",
    "admissionNumber": "WIN/2016/009"
  },
  {
    "sn": "10.",
    "name": "DIYAN KAREEMAH OLUWASEKEMI",
    "sex": "F",
    "class": "JSS 1",
    "section": "Secondary",
    "admissionNumber": "WIN/2016/010"
  },
  {
    "sn": "11.",
    "name": "DUWEIGHA AMSTRONG",
    "sex": "M",
    "class": "JSS 1",
    "section": "Secondary",
    "admissionNumber": "WIN/2016/011"
  },
  {
    "sn": "12.",
    "name": "IBRAHIM ABDULSAMAD",
    "sex": "M",
    "class": "JSS 1",
    "section": "Secondary",
    "admissionNumber": "WIN/2016/012"
  },
  {
    "sn": "13.",
    "name": "IGBOANUGO VICTORIA",
    "sex": "F",
    "class": "JSS 1",
    "section": "Secondary",
    "admissionNumber": "WIN/2016/013"
  },
  {
    "sn": "14.",
    "name": "IKHELOA PENIEL",
    "sex": "F",
    "class": "JSS 1",
    "section": "Secondary",
    "admissionNumber": "WIN/2016/014"
  },
  {
    "sn": "15.",
    "name": "JIMOH PEMISIRE",
    "sex": "F",
    "class": "JSS 1",
    "section": "Secondary",
    "admissionNumber": "WIN/2016/015"
  },
  {
    "sn": "16.",
    "name": "JONAH INEMESIT",
    "sex": "F",
    "class": "JSS 1",
    "section": "Secondary",
    "admissionNumber": "WIN/2016/016"
  },
  {
    "sn": "17.",
    "name": "MUSTAPHA OWODUNNI",
    "sex": "M",
    "class": "JSS 1",
    "section": "Secondary",
    "admissionNumber": "WIN/2016/017"
  },
  {
    "sn": "18.",
    "name": "OGUNLANA OLUWATOFUNMI",
    "sex": "F",
    "class": "JSS 1",
    "section": "Secondary",
    "admissionNumber": "WIN/2016/018"
  },
  {
    "sn": "19.",
    "name": "OKUSANYA AKOREDE",
    "sex": "M",
    "class": "JSS 1",
    "section": "Secondary",
    "admissionNumber": "WIN/2016/019"
  },
  {
    "sn": "20.",
    "name": "OLAINORE SAMUELS",
    "sex": "M",
    "class": "JSS 1",
    "section": "Secondary",
    "admissionNumber": "WIN/2016/020"
  },
  {
    "sn": "21.",
    "name": "OLANEYE WURAOLA",
    "sex": "F",
    "class": "JSS 1",
    "section": "Secondary",
    "admissionNumber": "WIN/2016/021"
  },
  {
    "sn": "22.",
    "name": "OLOFINLADE MORIRE",
    "sex": "F",
    "class": "JSS 1",
    "section": "Secondary",
    "admissionNumber": "WIN/2016/022"
  },
  {
    "sn": "23.",
    "name": "ORUMO RIDWAN",
    "sex": "M",
    "class": "JSS 1",
    "section": "Secondary",
    "admissionNumber": "WIN/2016/023"
  },
  {
    "sn": "24.",
    "name": "SEMILOLA GOODLUCK",
    "sex": "M",
    "class": "JSS 1",
    "section": "Secondary",
    "admissionNumber": "WIN/2016/024"
  },
  {
    "sn": "25.",
    "name": "SOTTIN BOLUWATIFE",
    "sex": "F",
    "class": "JSS 1",
    "section": "Secondary",
    "admissionNumber": "WIN/2016/025"
  },
  {
    "sn": "26.",
    "name": "TAIWO INIOLUWA",
    "sex": "F",
    "class": "JSS 1",
    "section": "Secondary",
    "admissionNumber": "WIN/2016/026"
  },
  {
    "sn": "27.",
    "name": "YUSUFF SOFIAT",
    "sex": "F",
    "class": "JSS 1",
    "section": "Secondary",
    "admissionNumber": "WIN/2016/027"
  },
  {
    "sn": "1.",
    "name": "ABUNMWENRE MICHELLE",
    "sex": "F",
    "class": "JSS 2",
    "section": "Secondary",
    "admissionNumber": "WIN/2015/001"
  },
  {
    "sn": "2.",
    "name": "ADEBNIYI FAIZAL",
    "sex": "M",
    "class": "JSS 2",
    "section": "Secondary",
    "admissionNumber": "WIN/2015/002"
  },
  {
    "sn": "3.",
    "name": "ADELEKE OWE",
    "sex": "M",
    "class": "JSS 2",
    "section": "Secondary",
    "admissionNumber": "WIN/2015/003"
  },
  {
    "sn": "4.",
    "name": "ADEMEFUN ISSAAC",
    "sex": "M",
    "class": "JSS 2",
    "section": "Secondary",
    "admissionNumber": "WIN/2015/004"
  },
  {
    "sn": "5.",
    "name": "ADEWUNMI   AMEEDAH",
    "sex": "F",
    "class": "JSS 2",
    "section": "Secondary",
    "admissionNumber": "WIN/2015/005"
  },
  {
    "sn": "6.",
    "name": "ADEYEMI HASSAN",
    "sex": "M",
    "class": "JSS 2",
    "section": "Secondary",
    "admissionNumber": "WIN/2015/006"
  },
  {
    "sn": "7.",
    "name": "ADEYEMI HUSEIN",
    "sex": "M",
    "class": "JSS 2",
    "section": "Secondary",
    "admissionNumber": "WIN/2015/007"
  },
  {
    "sn": "8.",
    "name": "AKINWEMIMO  EMMANUEL",
    "sex": "M",
    "class": "JSS 2",
    "section": "Secondary",
    "admissionNumber": "WIN/2015/008"
  },
  {
    "sn": "9.",
    "name": "ALLI JOSEPHINE E",
    "sex": "F",
    "class": "JSS 2",
    "section": "Secondary",
    "admissionNumber": "WIN/2015/009"
  },
  {
    "sn": "10.",
    "name": "ARIYO ELIZABETH",
    "sex": "F",
    "class": "JSS 2",
    "section": "Secondary",
    "admissionNumber": "WIN/2015/010"
  },
  {
    "sn": "11.",
    "name": "ASIEGBULE KELVIN",
    "sex": "M",
    "class": "JSS 2",
    "section": "Secondary",
    "admissionNumber": "WIN/2015/011"
  },
  {
    "sn": "12.",
    "name": "AYODELE OYINDAMOLA",
    "sex": "F",
    "class": "JSS 2",
    "section": "Secondary",
    "admissionNumber": "WIN/2015/012"
  },
  {
    "sn": "13.",
    "name": "CHIMA VICTOR",
    "sex": "F",
    "class": "JSS 2",
    "section": "Secondary",
    "admissionNumber": "WIN/2015/013"
  },
  {
    "sn": "14.",
    "name": "FESTUS DEBRAH",
    "sex": "F",
    "class": "JSS 2",
    "section": "Secondary",
    "admissionNumber": "WIN/2015/014"
  },
  {
    "sn": "15.",
    "name": "HASSAN  TENIOLA",
    "sex": "F",
    "class": "JSS 2",
    "section": "Secondary",
    "admissionNumber": "WIN/2015/015"
  },
  {
    "sn": "16.",
    "name": "ISEOLUWA   TIOLUWANI",
    "sex": "F",
    "class": "JSS 2",
    "section": "Secondary",
    "admissionNumber": "WIN/2015/016"
  },
  {
    "sn": "17.",
    "name": "JUNAID   OLUWAJOMILOJU",
    "sex": "F",
    "class": "JSS 2",
    "section": "Secondary",
    "admissionNumber": "WIN/2015/017"
  },
  {
    "sn": "18.",
    "name": "MUHAMMED H.OKIKIOLA",
    "sex": "M",
    "class": "JSS 2",
    "section": "Secondary",
    "admissionNumber": "WIN/2015/018"
  },
  {
    "sn": "19.",
    "name": "ODUNIYI  FAREEDAH",
    "sex": "F",
    "class": "JSS 2",
    "section": "Secondary",
    "admissionNumber": "WIN/2015/019"
  },
  {
    "sn": "20.",
    "name": "ODUWALE   ESTHER",
    "sex": "F",
    "class": "JSS 2",
    "section": "Secondary",
    "admissionNumber": "WIN/2015/020"
  },
  {
    "sn": "21.",
    "name": "OGUNMILORO MORAYO",
    "sex": "M",
    "class": "JSS 2",
    "section": "Secondary",
    "admissionNumber": "WIN/2015/021"
  },
  {
    "sn": "22.",
    "name": "OKECHUKWU   ANTHONY",
    "sex": "M",
    "class": "JSS 2",
    "section": "Secondary",
    "admissionNumber": "WIN/2015/022"
  },
  {
    "sn": "23.",
    "name": "OLABOSINDE  M.  SAMUEL",
    "sex": "M",
    "class": "JSS 2",
    "section": "Secondary",
    "admissionNumber": "WIN/2015/023"
  },
  {
    "sn": "24.",
    "name": "OLAOGUN  OLAMIPOSI",
    "sex": "M",
    "class": "JSS 2",
    "section": "Secondary",
    "admissionNumber": "WIN/2015/024"
  },
  {
    "sn": "25.",
    "name": "OLAWALE   FAWAZ",
    "sex": "M",
    "class": "JSS 2",
    "section": "Secondary",
    "admissionNumber": "WIN/2015/025"
  },
  {
    "sn": "26.",
    "name": "OLAYIWOLA    ENIOLA",
    "sex": "F",
    "class": "JSS 2",
    "section": "Secondary",
    "admissionNumber": "WIN/2015/026"
  },
  {
    "sn": "27.",
    "name": "OLULEYE   VICTORY",
    "sex": "F",
    "class": "JSS 2",
    "section": "Secondary",
    "admissionNumber": "WIN/2015/027"
  },
  {
    "sn": "28.",
    "name": "OLULEYE  VICTORIA",
    "sex": "F",
    "class": "JSS 2",
    "section": "Secondary",
    "admissionNumber": "WIN/2015/028"
  },
  {
    "sn": "29.",
    "name": "ONADEKO   DANIEL",
    "sex": "M",
    "class": "JSS 2",
    "section": "Secondary",
    "admissionNumber": "WIN/2015/029"
  },
  {
    "sn": "30.",
    "name": "ONUORA   C.  SOLOMON",
    "sex": "M",
    "class": "JSS 2",
    "section": "Secondary",
    "admissionNumber": "WIN/2015/030"
  },
  {
    "sn": "31.",
    "name": "SAHEED   DESIRE",
    "sex": "F",
    "class": "JSS 2",
    "section": "Secondary",
    "admissionNumber": "WIN/2015/031"
  },
  {
    "sn": "32.",
    "name": "SHODIYA   DANIEL",
    "sex": "M",
    "class": "JSS 2",
    "section": "Secondary",
    "admissionNumber": "WIN/2015/032"
  },
  {
    "sn": "33.",
    "name": "SULIAMON SOFIAT",
    "sex": "F",
    "class": "JSS 2",
    "section": "Secondary",
    "admissionNumber": "WIN/2015/033"
  },
  {
    "sn": "34.",
    "name": "WAHAB   OPEIFA",
    "sex": "F",
    "class": "JSS 2",
    "section": "Secondary",
    "admissionNumber": "WIN/2015/034"
  },
  {
    "sn": "35.",
    "name": "WEST    O.  AARON",
    "sex": "M",
    "class": "JSS 2",
    "section": "Secondary",
    "admissionNumber": "WIN/2015/035"
  },
  {
    "sn": "36.",
    "name": "YUSUF    INIOLUWA",
    "sex": "F",
    "class": "JSS 2",
    "section": "Secondary",
    "admissionNumber": "WIN/2015/036"
  },
  {
    "sn": "1.",
    "name": "ADEBAMBO  KHALID",
    "sex": "M",
    "class": "JSS 3A",
    "section": "Secondary",
    "admissionNumber": "WIN/undefined/001"
  },
  {
    "sn": "2.",
    "name": "ADEDEJI   ANJOLAOLUWA",
    "sex": "M",
    "class": "JSS 3A",
    "section": "Secondary",
    "admissionNumber": "WIN/undefined/002"
  },
  {
    "sn": "3.",
    "name": "ADEDOYIN   DANIELLA",
    "sex": "F",
    "class": "JSS 3A",
    "section": "Secondary",
    "admissionNumber": "WIN/undefined/003"
  },
  {
    "sn": "4.",
    "name": "ADEOLA   SALEM",
    "sex": "",
    "class": "JSS 3A",
    "section": "Secondary",
    "admissionNumber": "WIN/undefined/004"
  },
  {
    "sn": "5.",
    "name": "ADESOKAN   FUAD",
    "sex": "",
    "class": "JSS 3A",
    "section": "Secondary",
    "admissionNumber": "WIN/undefined/005"
  },
  {
    "sn": "6.",
    "name": "ADEWUYI   FUNMITO",
    "sex": "F",
    "class": "JSS 3A",
    "section": "Secondary",
    "admissionNumber": "WIN/undefined/006"
  },
  {
    "sn": "7.",
    "name": "ADEWUYI   OLUWAFUNMIKE",
    "sex": "",
    "class": "JSS 3A",
    "section": "Secondary",
    "admissionNumber": "WIN/undefined/007"
  },
  {
    "sn": "8.",
    "name": "ADEYEMI   ISEOLUWA",
    "sex": "F",
    "class": "JSS 3A",
    "section": "Secondary",
    "admissionNumber": "WIN/undefined/008"
  },
  {
    "sn": "9.",
    "name": "ADEYEMI  IYANUOLUWA",
    "sex": "F",
    "class": "JSS 3A",
    "section": "Secondary",
    "admissionNumber": "WIN/undefined/009"
  },
  {
    "sn": "10.",
    "name": "AHMED   ISRAEL",
    "sex": "",
    "class": "JSS 3A",
    "section": "Secondary",
    "admissionNumber": "WIN/undefined/010"
  },
  {
    "sn": "11.",
    "name": "AHMED  ABDULAHI",
    "sex": "M",
    "class": "JSS 3A",
    "section": "Secondary",
    "admissionNumber": "WIN/undefined/011"
  },
  {
    "sn": "12.",
    "name": "AJAYI  TOBILOBA",
    "sex": "F",
    "class": "JSS 3A",
    "section": "Secondary",
    "admissionNumber": "WIN/undefined/012"
  },
  {
    "sn": "13.",
    "name": "AKANDE   GOODNESS",
    "sex": "F",
    "class": "JSS 3A",
    "section": "Secondary",
    "admissionNumber": "WIN/undefined/013"
  },
  {
    "sn": "14.",
    "name": "ANIFOWOSHE   ANUOLUWAPO",
    "sex": "",
    "class": "JSS 3A",
    "section": "Secondary",
    "admissionNumber": "WIN/undefined/014"
  },
  {
    "sn": "15.",
    "name": "AWOLESI   OLUWABUSAYO",
    "sex": "",
    "class": "JSS 3A",
    "section": "Secondary",
    "admissionNumber": "WIN/undefined/015"
  },
  {
    "sn": "16.",
    "name": "AWOPEJU   USMAN",
    "sex": "",
    "class": "JSS 3A",
    "section": "Secondary",
    "admissionNumber": "WIN/undefined/016"
  },
  {
    "sn": "17.",
    "name": "BALOGUN   FAHEEDAT",
    "sex": "F",
    "class": "JSS 3A",
    "section": "Secondary",
    "admissionNumber": "WIN/undefined/017"
  },
  {
    "sn": "18.",
    "name": "DANIEL   STEPHANIE",
    "sex": "F",
    "class": "JSS 3A",
    "section": "Secondary",
    "admissionNumber": "WIN/undefined/018"
  },
  {
    "sn": "19.",
    "name": "INNOMESANGHAN  JOSEPH",
    "sex": "M",
    "class": "JSS 3A",
    "section": "Secondary",
    "admissionNumber": "WIN/undefined/019"
  },
  {
    "sn": "20.",
    "name": "IYIOLA   OBALOLUWA",
    "sex": "",
    "class": "JSS 3A",
    "section": "Secondary",
    "admissionNumber": "WIN/undefined/020"
  },
  {
    "sn": "21.",
    "name": "LUCKY  DANIEL",
    "sex": "M",
    "class": "JSS 3A",
    "section": "Secondary",
    "admissionNumber": "WIN/undefined/021"
  },
  {
    "sn": "22.",
    "name": "ODUNIKAN   ANJOLAOLUWA   DAVID",
    "sex": "",
    "class": "JSS 3A",
    "section": "Secondary",
    "admissionNumber": "WIN/undefined/022"
  },
  {
    "sn": "23.",
    "name": "OGUDIPE GRACE",
    "sex": "",
    "class": "JSS 3A",
    "section": "Secondary",
    "admissionNumber": "WIN/undefined/023"
  },
  {
    "sn": "24.",
    "name": "OKECHUKWU  VICTORIA",
    "sex": "",
    "class": "JSS 3A",
    "section": "Secondary",
    "admissionNumber": "WIN/undefined/024"
  },
  {
    "sn": "25.",
    "name": "OKOEGUALE   ARIELLA",
    "sex": "",
    "class": "JSS 3A",
    "section": "Secondary",
    "admissionNumber": "WIN/undefined/025"
  },
  {
    "sn": "26.",
    "name": "OLALEYE  OLUWATOFUNMI",
    "sex": "",
    "class": "JSS 3A",
    "section": "Secondary",
    "admissionNumber": "WIN/undefined/026"
  },
  {
    "sn": "27.",
    "name": "OLAROTIMI   MIRACLE",
    "sex": "",
    "class": "JSS 3A",
    "section": "Secondary",
    "admissionNumber": "WIN/undefined/027"
  },
  {
    "sn": "28.",
    "name": "OLAWORE    ISREAL",
    "sex": "M",
    "class": "JSS 3A",
    "section": "Secondary",
    "admissionNumber": "WIN/undefined/028"
  },
  {
    "sn": "29.",
    "name": "OLOWOLEKOMO ABIKE",
    "sex": "F",
    "class": "JSS 3A",
    "section": "Secondary",
    "admissionNumber": "WIN/undefined/029"
  },
  {
    "sn": "30.",
    "name": "OLUMEGBON   OLAMIDE",
    "sex": "",
    "class": "JSS 3A",
    "section": "Secondary",
    "admissionNumber": "WIN/undefined/030"
  },
  {
    "sn": "31.",
    "name": "OLUWAKEMI   JOSHUA",
    "sex": "",
    "class": "JSS 3A",
    "section": "Secondary",
    "admissionNumber": "WIN/undefined/031"
  },
  {
    "sn": "32.",
    "name": "ONUH FAITH ISAAC",
    "sex": "",
    "class": "JSS 3A",
    "section": "Secondary",
    "admissionNumber": "WIN/undefined/032"
  },
  {
    "sn": "33.",
    "name": "OPALADE  VICTOR",
    "sex": "M",
    "class": "JSS 3A",
    "section": "Secondary",
    "admissionNumber": "WIN/undefined/033"
  },
  {
    "sn": "34.",
    "name": "OSHINADE   IRESUKANMI",
    "sex": "M",
    "class": "JSS 3A",
    "section": "Secondary",
    "admissionNumber": "WIN/undefined/034"
  },
  {
    "sn": "35.",
    "name": "SALMAN HALIMAT",
    "sex": "F",
    "class": "JSS 3A",
    "section": "Secondary",
    "admissionNumber": "WIN/undefined/035"
  },
  {
    "sn": "36.",
    "name": "SHITTU   RODIAT",
    "sex": "",
    "class": "JSS 3A",
    "section": "Secondary",
    "admissionNumber": "WIN/undefined/036"
  },
  {
    "sn": "37.",
    "name": "SODUNKE  EMMANUEL",
    "sex": "",
    "class": "JSS 3A",
    "section": "Secondary",
    "admissionNumber": "WIN/undefined/037"
  },
  {
    "sn": "38.",
    "name": "TERRY NOAH",
    "sex": "",
    "class": "JSS 3A",
    "section": "Secondary",
    "admissionNumber": "WIN/undefined/038"
  },
  {
    "sn": "1.",
    "name": "ABEJOYE PHILIP",
    "sex": "M",
    "class": "JSS 3B",
    "section": "Secondary",
    "admissionNumber": "WIN/undefined/001"
  },
  {
    "sn": "2.",
    "name": "ABU HAMID",
    "sex": "M",
    "class": "JSS 3B",
    "section": "Secondary",
    "admissionNumber": "WIN/undefined/002"
  },
  {
    "sn": "3.",
    "name": "ADEBAYO JEREMIAH",
    "sex": "M",
    "class": "JSS 3B",
    "section": "Secondary",
    "admissionNumber": "WIN/undefined/003"
  },
  {
    "sn": "4.",
    "name": "ADEDOKUN AYOMIDE",
    "sex": "M",
    "class": "JSS 3B",
    "section": "Secondary",
    "admissionNumber": "WIN/undefined/004"
  },
  {
    "sn": "5.",
    "name": "ADEGOKE ADESEWA",
    "sex": "F",
    "class": "JSS 3B",
    "section": "Secondary",
    "admissionNumber": "WIN/undefined/005"
  },
  {
    "sn": "6.",
    "name": "ADEJARE HAPPINESS",
    "sex": "F",
    "class": "JSS 3B",
    "section": "Secondary",
    "admissionNumber": "WIN/undefined/006"
  },
  {
    "sn": "7.",
    "name": "ADEJORO BUSUYI",
    "sex": "M",
    "class": "JSS 3B",
    "section": "Secondary",
    "admissionNumber": "WIN/undefined/007"
  },
  {
    "sn": "8.",
    "name": "ADERETI JOHN",
    "sex": "M",
    "class": "JSS 3B",
    "section": "Secondary",
    "admissionNumber": "WIN/undefined/008"
  },
  {
    "sn": "9.",
    "name": "ADEYEMI SOFIYAH",
    "sex": "F",
    "class": "JSS 3B",
    "section": "Secondary",
    "admissionNumber": "WIN/undefined/009"
  },
  {
    "sn": "10.",
    "name": "AFINTIMI MOYOSOLUWA",
    "sex": "F",
    "class": "JSS 3B",
    "section": "Secondary",
    "admissionNumber": "WIN/undefined/010"
  },
  {
    "sn": "11.",
    "name": "AFOLABI OYINRISOLA",
    "sex": "M",
    "class": "JSS 3B",
    "section": "Secondary",
    "admissionNumber": "WIN/undefined/011"
  },
  {
    "sn": "12.",
    "name": "AKINBIOLA OLAWALE",
    "sex": "M",
    "class": "JSS 3B",
    "section": "Secondary",
    "admissionNumber": "WIN/undefined/012"
  },
  {
    "sn": "13.",
    "name": "AKOMOLAFE DANIEL",
    "sex": "M",
    "class": "JSS 3B",
    "section": "Secondary",
    "admissionNumber": "WIN/undefined/013"
  },
  {
    "sn": "14.",
    "name": "AKPAN JOAN",
    "sex": "F",
    "class": "JSS 3B",
    "section": "Secondary",
    "admissionNumber": "WIN/undefined/014"
  },
  {
    "sn": "15.",
    "name": "ALADE DANIELLA",
    "sex": "F",
    "class": "JSS 3B",
    "section": "Secondary",
    "admissionNumber": "WIN/undefined/015"
  },
  {
    "sn": "16.",
    "name": "ARIBIRO ABRAHAM",
    "sex": "M",
    "class": "JSS 3B",
    "section": "Secondary",
    "admissionNumber": "WIN/undefined/016"
  },
  {
    "sn": "17.",
    "name": "ASUPUTO SAMAD",
    "sex": "M",
    "class": "JSS 3B",
    "section": "Secondary",
    "admissionNumber": "WIN/undefined/017"
  },
  {
    "sn": "18.",
    "name": "AUDITOR FAITH",
    "sex": "F",
    "class": "JSS 3B",
    "section": "Secondary",
    "admissionNumber": "WIN/undefined/018"
  },
  {
    "sn": "19.",
    "name": "AWOKOYA ADEDAMOLA",
    "sex": "M",
    "class": "JSS 3B",
    "section": "Secondary",
    "admissionNumber": "WIN/undefined/019"
  },
  {
    "sn": "20.",
    "name": "DANIEL VICTOR",
    "sex": "M",
    "class": "JSS 3B",
    "section": "Secondary",
    "admissionNumber": "WIN/undefined/020"
  },
  {
    "sn": "21.",
    "name": "DARAMOLA OYINDAMOLA",
    "sex": "F",
    "class": "JSS 3B",
    "section": "Secondary",
    "admissionNumber": "WIN/undefined/021"
  },
  {
    "sn": "22.",
    "name": "EGODI JOEL",
    "sex": "M",
    "class": "JSS 3B",
    "section": "Secondary",
    "admissionNumber": "WIN/undefined/022"
  },
  {
    "sn": "23.",
    "name": "EGUAVOEN GREAT",
    "sex": "M",
    "class": "JSS 3B",
    "section": "Secondary",
    "admissionNumber": "WIN/undefined/023"
  },
  {
    "sn": "24.",
    "name": "EMERUWA PEREZ",
    "sex": "M",
    "class": "JSS 3B",
    "section": "Secondary",
    "admissionNumber": "WIN/undefined/024"
  },
  {
    "sn": "25.",
    "name": "EMERUWA PRECIOUS",
    "sex": "F",
    "class": "JSS 3B",
    "section": "Secondary",
    "admissionNumber": "WIN/undefined/025"
  },
  {
    "sn": "26.",
    "name": "FANUGA ADETOYE",
    "sex": "M",
    "class": "JSS 3B",
    "section": "Secondary",
    "admissionNumber": "WIN/undefined/026"
  },
  {
    "sn": "27.",
    "name": "FESTUS ESTHER",
    "sex": "F",
    "class": "JSS 3B",
    "section": "Secondary",
    "admissionNumber": "WIN/undefined/027"
  },
  {
    "sn": "28.",
    "name": "FUNZI JOYCE",
    "sex": "F",
    "class": "JSS 3B",
    "section": "Secondary",
    "admissionNumber": "WIN/undefined/028"
  },
  {
    "sn": "29.",
    "name": "IBUKUN OLUWATOBILOBA",
    "sex": "M",
    "class": "JSS 3B",
    "section": "Secondary",
    "admissionNumber": "WIN/undefined/029"
  },
  {
    "sn": "30.",
    "name": "IDEKPE EMMANUEL",
    "sex": "M",
    "class": "JSS 3B",
    "section": "Secondary",
    "admissionNumber": "WIN/undefined/030"
  },
  {
    "sn": "31.",
    "name": "ITA DIVINE",
    "sex": "M",
    "class": "JSS 3B",
    "section": "Secondary",
    "admissionNumber": "WIN/undefined/031"
  },
  {
    "sn": "32.",
    "name": "JOSEPH PRECIOUS",
    "sex": "F",
    "class": "JSS 3B",
    "section": "Secondary",
    "admissionNumber": "WIN/undefined/032"
  },
  {
    "sn": "33.",
    "name": "KANABE JOSEPH",
    "sex": "M",
    "class": "JSS 3B",
    "section": "Secondary",
    "admissionNumber": "WIN/undefined/033"
  },
  {
    "sn": "34.",
    "name": "KOLWOLE IBRAHIM",
    "sex": "M",
    "class": "JSS 3B",
    "section": "Secondary",
    "admissionNumber": "WIN/undefined/034"
  },
  {
    "sn": "35.",
    "name": "ODUNIKAN INIOLUWA",
    "sex": "M",
    "class": "JSS 3B",
    "section": "Secondary",
    "admissionNumber": "WIN/undefined/035"
  },
  {
    "sn": "36.",
    "name": "OLALEYE SAMUEL",
    "sex": "M",
    "class": "JSS 3B",
    "section": "Secondary",
    "admissionNumber": "WIN/undefined/036"
  },
  {
    "sn": "37.",
    "name": "OLAOGUN OLABISI",
    "sex": "M",
    "class": "JSS 3B",
    "section": "Secondary",
    "admissionNumber": "WIN/undefined/037"
  },
  {
    "sn": "38.",
    "name": "OLATUNJI QUYUM",
    "sex": "M",
    "class": "JSS 3B",
    "section": "Secondary",
    "admissionNumber": "WIN/undefined/038"
  },
  {
    "sn": "39.",
    "name": "OLUFOWORA EWA",
    "sex": "F",
    "class": "JSS 3B",
    "section": "Secondary",
    "admissionNumber": "WIN/undefined/039"
  },
  {
    "sn": "40.",
    "name": "OLUSHESI KHADIJAH",
    "sex": "F",
    "class": "JSS 3B",
    "section": "Secondary",
    "admissionNumber": "WIN/undefined/040"
  },
  {
    "sn": "41.",
    "name": "OMOTOSHO ELIZEBETH",
    "sex": "M",
    "class": "JSS 3B",
    "section": "Secondary",
    "admissionNumber": "WIN/undefined/041"
  },
  {
    "sn": "42.",
    "name": "ONUORA DESTINY",
    "sex": "M",
    "class": "JSS 3B",
    "section": "Secondary",
    "admissionNumber": "WIN/undefined/042"
  },
  {
    "sn": "43.",
    "name": "OYEDEPO KEHINDE",
    "sex": "M",
    "class": "JSS 3B",
    "section": "Secondary",
    "admissionNumber": "WIN/undefined/043"
  },
  {
    "sn": "44.",
    "name": "OYEDEPO TAIWO",
    "sex": "M",
    "class": "JSS 3B",
    "section": "Secondary",
    "admissionNumber": "WIN/undefined/044"
  },
  {
    "sn": "45.",
    "name": "PAUL PRECIOUS",
    "sex": "F",
    "class": "JSS 3B",
    "section": "Secondary",
    "admissionNumber": "WIN/undefined/045"
  },
  {
    "sn": "46.",
    "name": "SHODIYA MAYOWA",
    "sex": "F",
    "class": "JSS 3B",
    "section": "Secondary",
    "admissionNumber": "WIN/undefined/046"
  },
  {
    "sn": "47.",
    "name": "SOLAWON VICTOR",
    "sex": "M",
    "class": "JSS 3B",
    "section": "Secondary",
    "admissionNumber": "WIN/undefined/047"
  },
  {
    "sn": "48.",
    "name": "SOTTIN SEMILORE",
    "sex": "M",
    "class": "JSS 3B",
    "section": "Secondary",
    "admissionNumber": "WIN/undefined/048"
  },
  {
    "sn": "49.",
    "name": "SUNDAY BLESSING",
    "sex": "F",
    "class": "JSS 3B",
    "section": "Secondary",
    "admissionNumber": "WIN/undefined/049"
  },
  {
    "sn": "1.",
    "name": "ABEL   JOSEPH",
    "sex": "M",
    "class": "SS 1",
    "section": "Secondary",
    "admissionNumber": "WIN/2013/001"
  },
  {
    "sn": "2.",
    "name": "ADEBAYO   JUWON",
    "sex": "M",
    "class": "SS 1",
    "section": "Secondary",
    "admissionNumber": "WIN/2013/002"
  },
  {
    "sn": "3.",
    "name": "ADEMUYIWA  TOBI",
    "sex": "F",
    "class": "SS 1",
    "section": "Secondary",
    "admissionNumber": "WIN/2013/003"
  },
  {
    "sn": "4.",
    "name": "ADEOLA   ISREAL",
    "sex": "M",
    "class": "SS 1",
    "section": "Secondary",
    "admissionNumber": "WIN/2013/004"
  },
  {
    "sn": "5.",
    "name": "ADEYINKA   ADEBOLA",
    "sex": "F",
    "class": "SS 1",
    "section": "Secondary",
    "admissionNumber": "WIN/2013/005"
  },
  {
    "sn": "6.",
    "name": "AFINTINNI  FERANMI",
    "sex": "F",
    "class": "SS 1",
    "section": "Secondary",
    "admissionNumber": "WIN/2013/006"
  },
  {
    "sn": "7.",
    "name": "AGUOHA   DANIEL",
    "sex": "M",
    "class": "SS 1",
    "section": "Secondary",
    "admissionNumber": "WIN/2013/007"
  },
  {
    "sn": "8.",
    "name": "AJOSE RAPHAEL",
    "sex": "M",
    "class": "SS 1",
    "section": "Secondary",
    "admissionNumber": "WIN/2013/008"
  },
  {
    "sn": "9.",
    "name": "AKANU  STEPHANIE",
    "sex": "F",
    "class": "SS 1",
    "section": "Secondary",
    "admissionNumber": "WIN/2013/009"
  },
  {
    "sn": "10.",
    "name": "ANIFOWOSE  IREBAMI",
    "sex": "M",
    "class": "SS 1",
    "section": "Secondary",
    "admissionNumber": "WIN/2013/010"
  },
  {
    "sn": "11.",
    "name": "ATOLANI  EMMANUEL",
    "sex": "M",
    "class": "SS 1",
    "section": "Secondary",
    "admissionNumber": "WIN/2013/011"
  },
  {
    "sn": "12.",
    "name": "AYENI  JOY",
    "sex": "F",
    "class": "SS 1",
    "section": "Secondary",
    "admissionNumber": "WIN/2013/012"
  },
  {
    "sn": "13.",
    "name": "BANJO ADEBAYO",
    "sex": "M",
    "class": "SS 1",
    "section": "Secondary",
    "admissionNumber": "WIN/2013/013"
  },
  {
    "sn": "14.",
    "name": "BELLO  BOLADE",
    "sex": "M",
    "class": "SS 1",
    "section": "Secondary",
    "admissionNumber": "WIN/2013/014"
  },
  {
    "sn": "15.",
    "name": "CHIKEZIE  FRANK",
    "sex": "M",
    "class": "SS 1",
    "section": "Secondary",
    "admissionNumber": "WIN/2013/015"
  },
  {
    "sn": "16.",
    "name": "CHINEDU GRACE",
    "sex": "F",
    "class": "SS 1",
    "section": "Secondary",
    "admissionNumber": "WIN/2013/016"
  },
  {
    "sn": "17.",
    "name": "ESSIEN  MIRACLE",
    "sex": "M",
    "class": "SS 1",
    "section": "Secondary",
    "admissionNumber": "WIN/2013/017"
  },
  {
    "sn": "18.",
    "name": "FALEYE  GABRIEL",
    "sex": "M",
    "class": "SS 1",
    "section": "Secondary",
    "admissionNumber": "WIN/2013/018"
  },
  {
    "sn": "19.",
    "name": "IGBOANUGO    BENJAMIN",
    "sex": "M",
    "class": "SS 1",
    "section": "Secondary",
    "admissionNumber": "WIN/2013/019"
  },
  {
    "sn": "20.",
    "name": "JAIYESINMI  RAMADAN",
    "sex": "M",
    "class": "SS 1",
    "section": "Secondary",
    "admissionNumber": "WIN/2013/020"
  },
  {
    "sn": "21.",
    "name": "JOSEPH  CHIOMA",
    "sex": "F",
    "class": "SS 1",
    "section": "Secondary",
    "admissionNumber": "WIN/2013/021"
  },
  {
    "sn": "22.",
    "name": "JOSEPH CHIOMA",
    "sex": "F",
    "class": "SS 1",
    "section": "Secondary",
    "admissionNumber": "WIN/2013/022"
  },
  {
    "sn": "23.",
    "name": "JOSEPH VICTOR",
    "sex": "M",
    "class": "SS 1",
    "section": "Secondary",
    "admissionNumber": "WIN/2013/023"
  },
  {
    "sn": "24.",
    "name": "MUSTAPHA ABASS",
    "sex": "M",
    "class": "SS 1",
    "section": "Secondary",
    "admissionNumber": "WIN/2013/024"
  },
  {
    "sn": "25.",
    "name": "ODEJAYI  ABIKE  SEMIAT",
    "sex": "F",
    "class": "SS 1",
    "section": "Secondary",
    "admissionNumber": "WIN/2013/025"
  },
  {
    "sn": "26.",
    "name": "OGUNMILORO AYOBAMI",
    "sex": "M",
    "class": "SS 1",
    "section": "Secondary",
    "admissionNumber": "WIN/2013/026"
  },
  {
    "sn": "27.",
    "name": "OGUNMILORO RAMADAN",
    "sex": "M",
    "class": "SS 1",
    "section": "Secondary",
    "admissionNumber": "WIN/2013/027"
  },
  {
    "sn": "28.",
    "name": "OKOEGUALE   IVAN",
    "sex": "M",
    "class": "SS 1",
    "section": "Secondary",
    "admissionNumber": "WIN/2013/028"
  },
  {
    "sn": "29.",
    "name": "OKOLI JOHN",
    "sex": "M",
    "class": "SS 1",
    "section": "Secondary",
    "admissionNumber": "WIN/2013/029"
  },
  {
    "sn": "30.",
    "name": "OLADOKUN  ANJOLA",
    "sex": "F",
    "class": "SS 1",
    "section": "Secondary",
    "admissionNumber": "WIN/2013/030"
  },
  {
    "sn": "31.",
    "name": "OLAYEYE  MAYOWA",
    "sex": "M",
    "class": "SS 1",
    "section": "Secondary",
    "admissionNumber": "WIN/2013/031"
  },
  {
    "sn": "32.",
    "name": "OLUWAGBEMIGA   FAVOUR",
    "sex": "F",
    "class": "SS 1",
    "section": "Secondary",
    "admissionNumber": "WIN/2013/032"
  },
  {
    "sn": "33.",
    "name": "OLUWAKEMI  PRECIOUS",
    "sex": "F",
    "class": "SS 1",
    "section": "Secondary",
    "admissionNumber": "WIN/2013/033"
  },
  {
    "sn": "34.",
    "name": "ONUORA  MICHAEL",
    "sex": "M",
    "class": "SS 1",
    "section": "Secondary",
    "admissionNumber": "WIN/2013/034"
  },
  {
    "sn": "35.",
    "name": "OWOLABI  GAFAR",
    "sex": "M",
    "class": "SS 1",
    "section": "Secondary",
    "admissionNumber": "WIN/2013/035"
  },
  {
    "sn": "36.",
    "name": "OYEDEJO BOLUWATIFE",
    "sex": "F",
    "class": "SS 1",
    "section": "Secondary",
    "admissionNumber": "WIN/2013/036"
  },
  {
    "sn": "37.",
    "name": "OYINLOYE  KANYINSOLA",
    "sex": "F",
    "class": "SS 1",
    "section": "Secondary",
    "admissionNumber": "WIN/2013/037"
  },
  {
    "sn": "38.",
    "name": "RUFAI  TOLULOPE",
    "sex": "M",
    "class": "SS 1",
    "section": "Secondary",
    "admissionNumber": "WIN/2013/038"
  },
  {
    "sn": "39.",
    "name": "SHANU MOYO",
    "sex": "F",
    "class": "SS 1",
    "section": "Secondary",
    "admissionNumber": "WIN/2013/039"
  }
]
